pyutter/__init__.py
pyutter/core_routing.py
pyutter/core/primitive.py
pyutter/static/index.html
pyutter/static/viewController.js
pyutter/widgets/button.py
pyutter/widgets/form.py
pyutter/widgets/layout.py
pyutter/widgets/material.py
pyutter/widgets/text.py
pyutter-0.1.1.dist-info/LICENSE
pyutter-0.1.1.dist-info/WHEEL
pyutter-0.1.1.dist-info/METADATA
pyutter-0.1.1.dist-info/RECORD
